oparse
