Metadata-Version: 1.0
Name: oparse
Version: 0.9.2
Summary: oparse is a command line framework based on optparse.
Home-page: http://opensource.ollix.com/oparse
Author: Olli Wang
Author-email: olliwang@ollix.com
License: MIT
Platform: UNKNOWN
Classifier: Intended Audience :: Developers
Classifier: License :: OSI Approved
Classifier: Operating System :: OS Independent
Classifier: Programming Language :: Python
Classifier: Topic :: Terminals
